[
  {
    "Name": " 3 Idiots"
  },
  {
    "Name": " 3:10 to Yuma"
  },
  {
    "Name": " 8 Mile"
  },
  {
    "Name": " 9 (2009 animated)"
  },
  {
    "Name": " 10 Things I Hate About You"
  },
  {
    "Name": " 10th Kingdom, The"
  },
  {
    "Name": " 12 Angry Men"
  },
  {
    "Name": " 12 Years a Slave"
  },
  {
    "Name": " 13 Going on 30"
  },
  {
    "Name": " 13 Hours: The Secret Soldiers of Benghazi"
  },
  {
    "Name": " 13th Warrior, The"
  },
  {
    "Name": " 17 Again"
  },
  {
    "Name": " 20th Century Women"
  },
  {
    "Name": " 21 Grams"
  },
  {
    "Name": " 25th Hour"
  },
  {
    "Name": " 27 Dresses"
  },
  {
    "Name": " 28 Days Later"
  },
  {
    "Name": " 28 Weeks Later"
  },
  {
    "Name": " 40 Year-Old Virgin, The"
  },
  {
    "Name": " 50 First Dates"
  },
  {
    "Name": " 50/50 (2011)"
  },
  {
    "Name": " 400 Blows, The"
  },
  {
    "Name": " 127 Hours"
  },
  {
    "Name": " 300"
  },
  {
    "Name": " (500) Days of Summer"
  },
  {
    "Name": " 1408"
  },
  {
    "Name": " 1941"
  },
  {
    "Name": " 1969"
  },
  {
    "Name": " 2001: A Space Odyssey"
  },
  {
    "Name": " 2010: The Year We Make Contact"
  },
  {
    "Name": " 2012"
  },
  {
    "Name": " 2046"
  },
  {
    "Name": " 2081"
  },
  {
    "Name": " 3000 Miles to Graceland"
  },
  {
    "Name": " 20,000 Leagues Under the Sea"
  },
  {
    "Name": " 5,000 Fingers of Dr. T, The"
  },
  {
    "Name": " "
  },
  {
    "Name": " About Last Night..."
  },
  {
    "Name": " About Schmidt"
  },
  {
    "Name": " About Time"
  },
  {
    "Name": " Abraham Lincoln: Vampire Hunter"
  },
  {
    "Name": " Absence of Malice"
  },
  {
    "Name": " Absolute Power"
  },
  {
    "Name": " Accidental Tourist, The"
  },
  {
    "Name": " Accused, The (1988)"
  },
  {
    "Name": " Ace Ventura: Pet Detective"
  },
  {
    "Name": " Ace Ventura: When Nature Calls"
  },
  {
    "Name": " Across the Universe"
  },
  {
    "Name": " Act of Valor"
  },
  {
    "Name": " Adam's Rib"
  },
  {
    "Name": " Addams Family, The"
  },
  {
    "Name": " Adjustment Bureau, The"
  },
  {
    "Name": " Adventures of Pinocchio, The (1996)"
  },
  {
    "Name": " Adventures of Robin Hood, The"
  },
  {
    "Name": " Adventures of Rocky and Bullwinkle, The"
  },
  {
    "Name": " Adventures of Tintin, The"
  },
  {
    "Name": " Affair of the Necklace, The"
  },
  {
    "Name": " After Hours"
  },
  {
    "Name": " After Sex"
  },
  {
    "Name": " Aguirre, the Wrath of God"
  },
  {
    "Name": " A.I. Artificial Intelligence"
  },
  {
    "Name": " Air Bud"
  },
  {
    "Name": " Air Force One"
  },
  {
    "Name": " Airplane!"
  },
  {
    "Name": " Airplane II: The Sequel"
  },
  {
    "Name": " Airport"
  },
  {
    "Name": " Airport 1975"
  },
  {
    "Name": " Airport '77"
  },
  {
    "Name": " Akeelah and the Bee"
  },
  {
    "Name": " Akira"
  },
  {
    "Name": " Aladdin"
  },
  {
    "Name": " Aladdin and the King of Thieves"
  },
  {
    "Name": " Alamo, The (1960)"
  },
  {
    "Name": " Albatross"
  },
  {
    "Name": " Albino Alligator"
  },
  {
    "Name": " Alexander"
  },
  {
    "Name": " Alexander and the Terrible, Horrible, No Good, Very Bad Day"
  },
  {
    "Name": " Alice Doesn't Live Here Anymore"
  },
  {
    "Name": " Alice in Wonderland (1915)"
  },
  {
    "Name": " Alice in Wonderland (1951)"
  },
  {
    "Name": " Alice in Wonderland (1976)"
  },
  {
    "Name": " Alice in Wonderland (2010)"
  },
  {
    "Name": " Alice Through the Looking Glass"
  },
  {
    "Name": " Alien"
  },
  {
    "Name": " Alien 3"
  },
  {
    "Name": " Aliens (1986)"
  },
  {
    "Name": " Aliens in the Attic"
  },
  {
    "Name": " Alive (1993)"
  },
  {
    "Name": " All About My Mother"
  },
  {
    "Name": " All About Steve"
  },
  {
    "Name": " All Dogs Go to Heaven"
  },
  {
    "Name": " All Dogs Go to Heaven 2"
  },
  {
    "Name": " All of Me"
  },
  {
    "Name": " All the President's Men"
  },
  {
    "Name": " All the Right Moves"
  },
  {
    "Name": " Almost Famous"
  },
  {
    "Name": " Almost Heroes"
  },
  {
    "Name": " Along Came a Spider"
  },
  {
    "Name": " Alpha Dog"
  },
  {
    "Name": " Alpha and Omega"
  },
  {
    "Name": " Alvin and the Chipmunks"
  },
  {
    "Name": " Alvin and the Chipmunks: Chipwrecked"
  },
  {
    "Name": " Alvin and the Chipmunks: The Road Chip"
  },
  {
    "Name": " Alvin and the Chipmunks: The Squeakquel"
  },
  {
    "Name": " Amazing Spider-Man, The (2012)"
  },
  {
    "Name": " Amazing Spider-Man 2, The"
  },
  {
    "Name": " American Beauty"
  },
  {
    "Name": " American Chai"
  },
  {
    "Name": " American Gangster"
  },
  {
    "Name": " American Graffiti"
  },
  {
    "Name": " American History X"
  },
  {
    "Name": " American Hustle (2013)"
  },
  {
    "Name": " American in Paris, An"
  },
  {
    "Name": " American Me"
  },
  {
    "Name": " American Pie"
  },
  {
    "Name": " American Pie 2"
  },
  {
    "Name": " American Pie Presents: The Book Of love"
  },
  {
    "Name": " American Psycho"
  },
  {
    "Name": " American Reunion"
  },
  {
    "Name": " American Sniper"
  },
  {
    "Name": " American Tail, An"
  },
  {
    "Name": " American Tail: Fievel Goes West, An"
  },
  {
    "Name": " An American Tail: The Treasure of Manhattan Island, An"
  },
  {
    "Name": " American Wedding"
  },
  {
    "Name": " Americanization of Emily, The"
  },
  {
    "Name": " Amistad"
  },
  {
    "Name": " Amityville Horror, The (2005)"
  },
  {
    "Name": " Amour (2012)"
  },
  {
    "Name": " Anaconda"
  },
  {
    "Name": " Analyze This"
  },
  {
    "Name": " Anastasia (1997)"
  },
  {
    "Name": " Anchorman: The Legend of Ron Burgundy"
  },
  {
    "Name": " Anchorman 2: The Legend Continues"
  },
  {
    "Name": " …And Justice For All"
  },
  {
    "Name": " And the Band Played On"
  },
  {
    "Name": " Angel Eyes"
  },
  {
    "Name": " Angel Heart"
  },
  {
    "Name": " Angels & Demons"
  },
  {
    "Name": " Angels in the Outfield (1994)"
  },
  {
    "Name": " Angels with Dirty Faces"
  },
  {
    "Name": " Angus, Thongs and Perfect Snogging"
  },
  {
    "Name": " Angry Birds Movie, The"
  },
  {
    "Name": " Animal Farm (1999)"
  },
  {
    "Name": " Animal House"
  },
  {
    "Name": " Anna and the King"
  },
  {
    "Name": " Anna Karenina (2012)"
  },
  {
    "Name": " Annie"
  },
  {
    "Name": " Annie Hall"
  },
  {
    "Name": " Another Cinderella Story"
  },
  {
    "Name": " Ant Bully, The"
  },
  {
    "Name": " Antitrust"
  },
  {
    "Name": " Ant-Man"
  },
  {
    "Name": " Antz"
  },
  {
    "Name": " Apocalypse Now"
  },
  {
    "Name": " Apocalypto"
  },
  {
    "Name": " Apollo 13"
  },
  {
    "Name": " Apt Pupil"
  },
  {
    "Name": " Are We Done Yet?"
  },
  {
    "Name": " Are We There Yet?"
  },
  {
    "Name": " Argo (2012)"
  },
  {
    "Name": " Aristocats, The"
  },
  {
    "Name": " Armageddon"
  },
  {
    "Name": " Around the World in 80 Days (2004)"
  },
  {
    "Name": " Arrival"
  },
  {
    "Name": " Arsenic and Old Lace"
  },
  {
    "Name": " Arthur"
  },
  {
    "Name": " As Good As It Gets"
  },
  {
    "Name": " Assassination Games"
  },
  {
    "Name": " Assassination of a High School President"
  },
  {
    "Name": " Assassination of Jesse James by the Coward Robert Ford, The"
  },
  {
    "Name": " At First Sight"
  },
  {
    "Name": " Atlantic City (1980)"
  },
  {
    "Name": " Atlantis: The Lost Empire"
  },
  {
    "Name": " ATM"
  },
  {
    "Name": " Atonement"
  },
  {
    "Name": " Attack of the 50 Foot Woman"
  },
  {
    "Name": " August Rush"
  },
  {
    "Name": " Austin Powers in Goldmember"
  },
  {
    "Name": " Austin Powers: International Man of Mystery"
  },
  {
    "Name": " Austin Powers: The Spy Who Shagged Me"
  },
  {
    "Name": " Australia"
  },
  {
    "Name": " Avatar"
  },
  {
    "Name": " Avengers, The (2012)"
  },
  {
    "Name": " Aviator, The"
  },
  {
    "Name": " Away from Her"
  },
  {
    "Name": " "
  },
  {
    "Name": " Babe"
  },
  {
    "Name": " Babe, The"
  },
  {
    "Name": " Babylon A.D"
  },
  {
    "Name": " Bachelor Mother"
  },
  {
    "Name": " Bachelorette"
  },
  {
    "Name": " Back to School"
  },
  {
    "Name": " Back to the Future"
  },
  {
    "Name": " Back to the Future Part II"
  },
  {
    "Name": " Back to the Future Part III"
  },
  {
    "Name": " Backdraft"
  },
  {
    "Name": " Bad and the Beautiful, The"
  },
  {
    "Name": " Bad Boys (1995)"
  },
  {
    "Name": " Bad Boys II"
  },
  {
    "Name": " Bad Day at Black Rock"
  },
  {
    "Name": " Bad Santa"
  },
  {
    "Name": " Bad Taste"
  },
  {
    "Name": " Badlands"
  },
  {
    "Name": " Balto"
  },
  {
    "Name": " Bambi"
  },
  {
    "Name": " Bambi II"
  },
  {
    "Name": " Bananas"
  },
  {
    "Name": " Barbarella"
  },
  {
    "Name": " Barcelona"
  },
  {
    "Name": " Barry Lyndon"
  },
  {
    "Name": " Barton Fink"
  },
  {
    "Name": " BASEketball"
  },
  {
    "Name": " Basic Instinct"
  },
  {
    "Name": " Basic Instinct 2"
  },
  {
    "Name": " Batman (1989)"
  },
  {
    "Name": " Batman Begins"
  },
  {
    "Name": " Batman Forever"
  },
  {
    "Name": " Batman Returns"
  },
  {
    "Name": " Batman v Superman: Dawn of Justice"
  },
  {
    "Name": " Battle: Los Angeles"
  },
  {
    "Name": " Battle of San Pietro, The"
  },
  {
    "Name": " Battle Royale"
  },
  {
    "Name": " Be Kind Rewind"
  },
  {
    "Name": " Beach, The"
  },
  {
    "Name": " Beaches"
  },
  {
    "Name": " Bean (1997)"
  },
  {
    "Name": " Beasts of the Southern Wild"
  },
  {
    "Name": " Beast of Yucca Flats, The"
  },
  {
    "Name": " Beau Geste (1939)"
  },
  {
    "Name": " Beautiful Girls"
  },
  {
    "Name": " Beautiful Mind, A"
  },
  {
    "Name": " Beautiful Thing"
  },
  {
    "Name": " Beauty and the Beast (1991)"
  },
  {
    "Name": " Beauty and the Beast (2017)"
  },
  {
    "Name": " Beavis and Butthead Do America"
  },
  {
    "Name": " Becoming Jane"
  },
  {
    "Name": " Bedazzled (1967)"
  },
  {
    "Name": " Bedazzled (2000)"
  },
  {
    "Name": " Bedknobs and Broomsticks"
  },
  {
    "Name": " Bedtime Stories"
  },
  {
    "Name": " Bee Movie"
  },
  {
    "Name": " Bee Season"
  },
  {
    "Name": " Beerfest"
  },
  {
    "Name": " Beetlejuice"
  },
  {
    "Name": " Before Midnight"
  },
  {
    "Name": " Before Sunrise"
  },
  {
    "Name": " Before Sunset"
  },
  {
    "Name": " Beginners"
  },
  {
    "Name": " Behind Enemy Lines"
  },
  {
    "Name": " Behind the Candelabra"
  },
  {
    "Name": " Being John Malkovich"
  },
  {
    "Name": " Being There"
  },
  {
    "Name": " Believer, The"
  },
  {
    "Name": " Ben-Hur (1959)"
  },
  {
    "Name": " Bend It Like Beckham"
  },
  {
    "Name": " Benny & Joon"
  },
  {
    "Name": " Beowulf"
  },
  {
    "Name": " Best in Show"
  },
  {
    "Name": " Best Laid Plans"
  },
  {
    "Name": " Best Little Whorehouse in Texas, The"
  },
  {
    "Name": " Best Years of Our Lives, The"
  },
  {
    "Name": " Better Off Dead"
  },
  {
    "Name": " Better Than Chocolate"
  },
  {
    "Name": " Better Tomorrow, A"
  },
  {
    "Name": " Beverly Hills Chihuahua"
  },
  {
    "Name": " Beverly Hills Cop II"
  },
  {
    "Name": " Beverly Hills Cop III"
  },
  {
    "Name": " Beyond the Valley of the Dolls"
  },
  {
    "Name": " Bicentennial Man"
  },
  {
    "Name": " Bicycle Thieves"
  },
  {
    "Name": " Big"
  },
  {
    "Name": " Big Chill, The"
  },
  {
    "Name": " Big Daddy"
  },
  {
    "Name": " Big Easy, The"
  },
  {
    "Name": " Big Fat Liar"
  },
  {
    "Name": " Big Fish"
  },
  {
    "Name": " Big Hero 6"
  },
  {
    "Name": " Big Lebowski, The"
  },
  {
    "Name": " Big Night"
  },
  {
    "Name": " Big Short, The"
  },
  {
    "Name": " Big Sleep, The (1946)"
  },
  {
    "Name": " Big Top Pee-wee"
  },
  {
    "Name": " Big Trouble"
  },
  {
    "Name": " Big Trouble in Little China"
  },
  {
    "Name": " Bill and Ted's Bogus Journey"
  },
  {
    "Name": " Bill and Ted's Excellent Adventure"
  },
  {
    "Name": " Billy Madison"
  },
  {
    "Name": " Birdman"
  },
  {
    "Name": " Birds, The"
  },
  {
    "Name": " Black Book"
  },
  {
    "Name": " Black Cat, The (1934)"
  },
  {
    "Name": " Black Christmas (1974)"
  },
  {
    "Name": " Black Christmas (2006)"
  },
  {
    "Name": " Black Hawk Down"
  },
  {
    "Name": " Black Hole, The"
  },
  {
    "Name": " Black Rain"
  },
  {
    "Name": " Black Sheep"
  },
  {
    "Name": " Black Swan"
  },
  {
    "Name": " Blade"
  },
  {
    "Name": " Blade II"
  },
  {
    "Name": " Blade Runner"
  },
  {
    "Name": " Blade: Trinity"
  },
  {
    "Name": " Blades of Glory"
  },
  {
    "Name": " Blair Witch Project, The"
  },
  {
    "Name": " Blazing Saddles"
  },
  {
    "Name": " Blind Date (1987)"
  },
  {
    "Name": " Blob, The (1958)"
  },
  {
    "Name": " Blood Diamond"
  },
  {
    "Name": " Blood Feast"
  },
  {
    "Name": " Blood Simple"
  },
  {
    "Name": " Blow"
  },
  {
    "Name": " Blow Out"
  },
  {
    "Name": " Blown Away (1994)"
  },
  {
    "Name": " Blue Collar"
  },
  {
    "Name": " Blue Lagoon, The"
  },
  {
    "Name": " Blue Jasmine"
  },
  {
    "Name": " Blue Velvet"
  },
  {
    "Name": " Blues Brothers, The"
  },
  {
    "Name": " Blues Brothers 2000"
  },
  {
    "Name": " Body Heat"
  },
  {
    "Name": " Body of Lies"
  },
  {
    "Name": " Boiler Room"
  },
  {
    "Name": " Bold Caballero, The"
  },
  {
    "Name": " Bolt (2008)"
  },
  {
    "Name": " Boogeyman"
  },
  {
    "Name": " Book of Life, The"
  },
  {
    "Name": " Book of Pooh: Stories from the Heart, The"
  },
  {
    "Name": " Book of Shadows: Blair Witch 2"
  },
  {
    "Name": " Book Thief, The"
  },
  {
    "Name": " Boondock Saints, The"
  },
  {
    "Name": " Borat: Cultural Learnings of America for Make Benefit Glorious Nation of Kazakhstan"
  },
  {
    "Name": " Born on the Fourth of July"
  },
  {
    "Name": " Bottle Rocket"
  },
  {
    "Name": " Bound"
  },
  {
    "Name": " Bourne Identity, The"
  },
  {
    "Name": " Bourne Legacy, The"
  },
  {
    "Name": " Bourne Supremacy, The"
  },
  {
    "Name": " Bourne Ultimatum, The"
  },
  {
    "Name": " Bowling for Columbine"
  },
  {
    "Name": " Box-Office Bunny"
  },
  {
    "Name": " Boy Named Charlie Brown, A"
  },
  {
    "Name": " Boyhood"
  },
  {
    "Name": " Boys from Brazil, The"
  },
  {
    "Name": " Boys Next Door, The"
  },
  {
    "Name": " Boys Town"
  },
  {
    "Name": " Boyz n the Hood"
  },
  {
    "Name": " Braindead"
  },
  {
    "Name": " Brassed Off"
  },
  {
    "Name": " Brave (2012)"
  },
  {
    "Name": " Braveheart"
  },
  {
    "Name": " Brazil"
  },
  {
    "Name": " Breakfast at Tiffany's"
  },
  {
    "Name": " Breakfast Club, The"
  },
  {
    "Name": " Breaking Away"
  },
  {
    "Name": " Breaking Up"
  },
  {
    "Name": " Brian's Song"
  },
  {
    "Name": " Bride of Chucky"
  },
  {
    "Name": " Bride Wars"
  },
  {
    "Name": " Bridge of Spies"
  },
  {
    "Name": " Bridge on the River Kwai, The"
  },
  {
    "Name": " Bridge to Terabithia (2007)"
  },
  {
    "Name": " Bridget Jones's Diary"
  },
  {
    "Name": " Bring It On"
  },
  {
    "Name": " Bring Me the Head of Alfredo Garcia"
  },
  {
    "Name": " Bringing Up Baby"
  },
  {
    "Name": " Broadcast News"
  },
  {
    "Name": " Brokeback Mountain"
  },
  {
    "Name": " Broken Arrow"
  },
  {
    "Name": " Bronx Tale, A"
  },
  {
    "Name": " Brooklyn"
  },
  {
    "Name": " Brother Bear"
  },
  {
    "Name": " Brother Bear 2"
  },
  {
    "Name": " Brothers Grimm, The"
  },
  {
    "Name": " Brothers McMullen, The"
  },
  {
    "Name": " Brothers Solomon, The"
  },
  {
    "Name": " Brubaker"
  },
  {
    "Name": " Bruce Almighty"
  },
  {
    "Name": " Buckaroo Banzai"
  },
  {
    "Name": " Bucket List, The"
  },
  {
    "Name": " Buffalo '66"
  },
  {
    "Name": " Buffy the Vampire Slayer"
  },
  {
    "Name": " Bug"
  },
  {
    "Name": " Bug's Life, A"
  },
  {
    "Name": " Bull Durham"
  },
  {
    "Name": " Bullfighters, The"
  },
  {
    "Name": " Bullitt"
  },
  {
    "Name": " Burn After Reading"
  },
  {
    "Name": " But I'm a Cheerleader"
  },
  {
    "Name": " Butch Cassidy and the Sundance Kid"
  },
  {
    "Name": " Butterfly Effect, The"
  },
  {
    "Name": " By Dawn's Early Light"
  },
  {
    "Name": " "
  },
  {
    "Name": " Cabin Fever"
  },
  {
    "Name": " Cabin in the Woods, The"
  },
  {
    "Name": " Cabinet of Dr. Caligari, The"
  },
  {
    "Name": " Cable Guy, The"
  },
  {
    "Name": " Caddyshack"
  },
  {
    "Name": " Caine Mutiny, The"
  },
  {
    "Name": " Camelot"
  },
  {
    "Name": " Camille (1936)"
  },
  {
    "Name": " Camp Rock"
  },
  {
    "Name": " Can't Buy Me Love"
  },
  {
    "Name": " Can't Hardly Wait"
  },
  {
    "Name": " Candy (2006)"
  },
  {
    "Name": " Cape Fear (1991)"
  },
  {
    "Name": " Capricorn One"
  },
  {
    "Name": " Captain America: Civil War"
  },
  {
    "Name": " Captain America: The First Avenger"
  },
  {
    "Name": " Captain America: The Winter Soldier"
  },
  {
    "Name": " Captain Phillips"
  },
  {
    "Name": " Care Bears Movie, The"
  },
  {
    "Name": " Care Bears Movie II: A New Generation"
  },
  {
    "Name": " Carlito's Way"
  },
  {
    "Name": " Carnal Knowledge"
  },
  {
    "Name": " Carol"
  },
  {
    "Name": " Carrie (1976)"
  },
  {
    "Name": " Carrie (2002)"
  },
  {
    "Name": " Carrie (2013)"
  },
  {
    "Name": " Cars"
  },
  {
    "Name": " Cars 2"
  },
  {
    "Name": " Casablanca"
  },
  {
    "Name": " Casanova"
  },
  {
    "Name": " Casino"
  },
  {
    "Name": " Casino Royale"
  },
  {
    "Name": " Cast Away"
  },
  {
    "Name": " Casualties of War"
  },
  {
    "Name": " Cat in the Hat, The (2003)"
  },
  {
    "Name": " Cat on a Hot Tin Roof"
  },
  {
    "Name": " Cat People (1942)"
  },
  {
    "Name": " Cat Returns, The"
  },
  {
    "Name": " Catch-22"
  },
  {
    "Name": " Catch Me If You Can"
  },
  {
    "Name": " Cats & Dogs"
  },
  {
    "Name": " Cats & Dogs: The Revenge of Kitty Galore"
  },
  {
    "Name": " Cats Don't Dance"
  },
  {
    "Name": " Catwoman"
  },
  {
    "Name": " Cecil B. Demented"
  },
  {
    "Name": " Champion (1949)"
  },
  {
    "Name": " Changing Lanes"
  },
  {
    "Name": " Charlie and the Chocolate Factory (2005)"
  },
  {
    "Name": " Charlie's Angels"
  },
  {
    "Name": " Charlie's Angels: Full Throttle"
  },
  {
    "Name": " Charlie Wilson's War"
  },
  {
    "Name": " Chariots of Fire"
  },
  {
    "Name": " Charlotte's Web (1973)"
  },
  {
    "Name": " Chasing Amy"
  },
  {
    "Name": " Chasing Liberty"
  },
  {
    "Name": " Cheaper by the Dozen (1950)"
  },
  {
    "Name": " Cheaper by the Dozen (2003)"
  },
  {
    "Name": " Cheaper by the Dozen 2"
  },
  {
    "Name": " Cheech & Chong's Next Movie"
  },
  {
    "Name": " Cheech & Chong's The Corsican Brothers"
  },
  {
    "Name": " Chicago (2002)"
  },
  {
    "Name": " Chicken Run"
  },
  {
    "Name": " Children of Dune"
  },
  {
    "Name": " Children of Men"
  },
  {
    "Name": " Children of Paradise"
  },
  {
    "Name": " Children of the Corn"
  },
  {
    "Name": " Children's Hour, The"
  },
  {
    "Name": " Child's Play"
  },
  {
    "Name": " Child's Play 2"
  },
  {
    "Name": " Child's Play 3"
  },
  {
    "Name": " Chinatown"
  },
  {
    "Name": " Chitty Chitty Bang Bang"
  },
  {
    "Name": " Chloe"
  },
  {
    "Name": " Chocolat"
  },
  {
    "Name": " Choke"
  },
  {
    "Name": " Chorus Line, A"
  },
  {
    "Name": " Christine"
  },
  {
    "Name": " Christmas Carol, A (2009)"
  },
  {
    "Name": " Christmas Story, A"
  },
  {
    "Name": " Christmas with the Kranks"
  },
  {
    "Name": " Chronicle"
  },
  {
    "Name": " Chronicles of Narnia: Prince Caspian, The"
  },
  {
    "Name": " Chronicles of Narnia: The Lion, the Witch and the Wardrobe, The"
  },
  {
    "Name": " Chronicles of Narnia: The Voyage of the Dawn Treader, The"
  },
  {
    "Name": " Chronicles of Riddick, The"
  },
  {
    "Name": " Chumscrubber, The"
  },
  {
    "Name": " Chungking Express"
  },
  {
    "Name": " Cider House Rules, The"
  },
  {
    "Name": " Cincinnati Kid, The"
  },
  {
    "Name": " Cinderella (1950)"
  },
  {
    "Name": " Cinderella (2015)"
  },
  {
    "Name": " Cinderella Story, A"
  },
  {
    "Name": " Citizen Kane"
  },
  {
    "Name": " City of Angels"
  },
  {
    "Name": " City of Ember"
  },
  {
    "Name": " City on Fire (1979)"
  },
  {
    "Name": " City of God"
  },
  {
    "Name": " City Slickers"
  },
  {
    "Name": " Clash of the Titans (2010)"
  },
  {
    "Name": " Class of Nuke 'Em High"
  },
  {
    "Name": " Clean and Sober"
  },
  {
    "Name": " Clear and Present Danger"
  },
  {
    "Name": " Cleopatra (1963)"
  },
  {
    "Name": " Click"
  },
  {
    "Name": " Client, The"
  },
  {
    "Name": " Clerks"
  },
  {
    "Name": " Clerks II"
  },
  {
    "Name": " Clockwise"
  },
  {
    "Name": " Clockwork Orange, A"
  },
  {
    "Name": " Close Encounters Of The Third Kind"
  },
  {
    "Name": " Closer"
  },
  {
    "Name": " Cloudy with a Chance of Meatballs"
  },
  {
    "Name": " Cloudy with a Chance of Meatballs 2"
  },
  {
    "Name": " Cloverfield"
  },
  {
    "Name": " Clue"
  },
  {
    "Name": " Clueless"
  },
  {
    "Name": " Coach Carter"
  },
  {
    "Name": " Cocktail"
  },
  {
    "Name": " Color Purple, The"
  },
  {
    "Name": " Cold Mountain"
  },
  {
    "Name": " Collateral"
  },
  {
    "Name": " Coma"
  },
  {
    "Name": " Coming Home"
  },
  {
    "Name": " Commando"
  },
  {
    "Name": " Commitments, The"
  },
  {
    "Name": " Compulsion"
  },
  {
    "Name": " Con Air"
  },
  {
    "Name": " Conan the Barbarian"
  },
  {
    "Name": " Conan the Destroyer"
  },
  {
    "Name": " Coneheads"
  },
  {
    "Name": " Confessions of a Dangerous Mind"
  },
  {
    "Name": " Confetti"
  },
  {
    "Name": " Conquest of Space"
  },
  {
    "Name": " Conspiracy Theory"
  },
  {
    "Name": " Constant Gardener, The"
  },
  {
    "Name": " Constantine"
  },
  {
    "Name": " Contagion"
  },
  {
    "Name": " Control (2007)"
  },
  {
    "Name": " Cool and the Crazy‎"
  },
  {
    "Name": " Cool Hand Luke"
  },
  {
    "Name": " Cool Runnings"
  },
  {
    "Name": " Cool World"
  },
  {
    "Name": " Cop and a Half"
  },
  {
    "Name": " Coraline"
  },
  {
    "Name": " Core, The"
  },
  {
    "Name": " Corpse Bride"
  },
  {
    "Name": " Contact"
  },
  {
    "Name": " Court Jester, The"
  },
  {
    "Name": " Count of Monte Cristo, The (2002)"
  },
  {
    "Name": " Courtship Of Eddie's Father, The (1963)"
  },
  {
    "Name": " Cowboy Bebop: The Movie"
  },
  {
    "Name": " Coyote Ugly"
  },
  {
    "Name": " Craft, The"
  },
  {
    "Name": " Crank"
  },
  {
    "Name": " Crash (2004)"
  },
  {
    "Name": " Crimes and Misdemeanors"
  },
  {
    "Name": " Crimewave"
  },
  {
    "Name": " Crimson Tide"
  },
  {
    "Name": " Criss Cross (1949)"
  },
  {
    "Name": " Crocodile Dundee"
  },
  {
    "Name": " Crocodile Dundee in Los Angeles"
  },
  {
    "Name": " Croods, The"
  },
  {
    "Name": " Cross of Iron"
  },
  {
    "Name": " Crouching Tiger, Hidden Dragon"
  },
  {
    "Name": " Crow, The"
  },
  {
    "Name": " Crow: City Of Angels, The"
  },
  {
    "Name": " Cry Freedom"
  },
  {
    "Name": " Cry Wolf"
  },
  {
    "Name": " Cruel Intentions"
  },
  {
    "Name": " Crying Game, The"
  },
  {
    "Name": " Cube"
  },
  {
    "Name": " Cube 2: Hypercube"
  },
  {
    "Name": " Cube Zero"
  },
  {
    "Name": " Cure, The (1995)"
  },
  {
    "Name": " Curious Case of Benjamin Button, The"
  },
  {
    "Name": " Curious George"
  },
  {
    "Name": " Cursed (2005)"
  },
  {
    "Name": " Cutting Edge, The"
  },
  {
    "Name": " Commando: Clash of the Warriors (film)"
  },
  {
    "Name": " "
  },
  {
    "Name": " 100 Days (1991)"
  },
  {
    "Name": " 100 Days (2001)"
  },
  {
    "Name": " 10,000 BC"
  },
  {
    "Name": " 11th Hour, The"
  },
  {
    "Name": " 13 Moons"
  },
  {
    "Name": " 15 Minutes"
  },
  {
    "Name": " 16 Years of Alcohol"
  },
  {
    "Name": " 187"
  },
  {
    "Name": " 18000 Dead in Gordon Head"
  },
  {
    "Name": " 24"
  },
  {
    "Name": " 3 O'Clock High"
  },
  {
    "Name": " 30 Days of Night"
  },
  {
    "Name": " 5 centimeters per second"
  },
  {
    "Name": " 5x2"
  },
  {
    "Name": " 51st State, The"
  },
  {
    "Name": " 55 Days at Peking"
  },
  {
    "Name": " 7 Samurai"
  },
  {
    "Name": " 7 Years In Tibet"
  },
  {
    "Name": " 84 Charing Cross Road"
  },
  {
    "Name": " 88 Minutes"
  },
  {
    "Name": " 800 Bullets"
  },
  {
    "Name": " 61*"
  },
  {
    "Name": " 9"
  },
  {
    "Name": " 99 franks"
  },
  {
    "Name": " 300 Pound Beauty"
  },
  {
    "Name": " "
  },
  {
    "Name": " Accidental Spy, The"
  },
  {
    "Name": " Actors, The"
  },
  {
    "Name": " Addicted to Love"
  },
  {
    "Name": " Adjustment Bureau, The"
  },
  {
    "Name": " Adventures of Don Juan, The"
  },
  {
    "Name": " Adventures of Ichabod and Mr. Toad, The"
  },
  {
    "Name": " Adventures of Milo and Otis, The"
  },
  {
    "Name": " Afterglow"
  },
  {
    "Name": " Against the Ropes"
  },
  {
    "Name": " Age of Adaline"
  },
  {
    "Name": " Akaler Sandhane (a.k.a. In Search of Famine)"
  },
  {
    "Name": " The Alamo (2004)"
  },
  {
    "Name": " Alexander Nevsky"
  },
  {
    "Name": " Alexandra's Project"
  },
  {
    "Name": " Alias Betty"
  },
  {
    "Name": " Alien Autopsy"
  },
  {
    "Name": " Alien Nation"
  },
  {
    "Name": " Alien: Resurrection"
  },
  {
    "Name": " Aliens vs. Predator: Requiem"
  },
  {
    "Name": " Aliens of the Deep"
  },
  {
    "Name": " All About the Benjamins"
  },
  {
    "Name": " All or Nothing"
  },
  {
    "Name": " All the Pretty Horses"
  },
  {
    "Name": " All the Queen's Men"
  },
  {
    "Name": " Almost Peaceful"
  },
  {
    "Name": " Alone in the Dark"
  },
  {
    "Name": " Alucarda"
  },
  {
    "Name": " Amati Girls, The"
  },
  {
    "Name": " Amazing Grace"
  },
  {
    "Name": " Amazing Panda Adventure, The"
  },
  {
    "Name": " American Astronaut, The"
  },
  {
    "Name": " American Friend, The"
  },
  {
    "Name": " American Pie 5 Naked Mile"
  },
  {
    "Name": " American Pie: Beta House"
  },
  {
    "Name": " American Yakuza"
  },
  {
    "Name": " An American Rhapsody"
  },
  {
    "Name": " Anacondas: The Hunt for the Blood Orchid"
  },
  {
    "Name": " Andre"
  },
  {
    "Name": " Angel-A"
  },
  {
    "Name": " Annie (2014 film)"
  },
  {
    "Name": " Anniversary Party, The"
  },
  {
    "Name": " Another Gay Movie"
  },
  {
    "Name": " Antwone Fisher"
  },
  {
    "Name": " Antz 2"
  },
  {
    "Name": " Any Way the Wind Blows"
  },
  {
    "Name": " Apartment Zero"
  },
  {
    "Name": " Apollo 18"
  },
  {
    "Name": " Arabian Knight (aka The Thief and the Cobbler)"
  },
  {
    "Name": " Artists and Models"
  },
  {
    "Name": " Around the World in 80 Days"
  },
  {
    "Name": " As It Is in Heaven"
  },
  {
    "Name": " Astronaut Farmer, The"
  },
  {
    "Name": " Athadu"
  },
  {
    "Name": " Attack On Leningrad"
  },
  {
    "Name": " Autumn in New York"
  },
  {
    "Name": " Anuvahood"
  },
  {
    "Name": " "
  },
  {
    "Name": " Babe: Pig in the City"
  },
  {
    "Name": " Baby Boom"
  },
  {
    "Name": " Babyboy"
  },
  {
    "Name": " Baby Mama"
  },
  {
    "Name": " Baltimore Bullet, The"
  },
  {
    "Name": " Basketball Diaries"
  },
  {
    "Name": " Barnyard"
  },
  {
    "Name": " Barry Munday"
  },
  {
    "Name": " Battle Beyond the Stars"
  },
  {
    "Name": " Beaches"
  },
  {
    "Name": " Beautician and the Beast, The"
  },
  {
    "Name": " Beautiful People"
  },
  {
    "Name": " Beauty and the Beast (2017)"
  },
  {
    "Name": " Beaver, The"
  },
  {
    "Name": " Beaver Trilogy, The"
  },
  {
    "Name": " Because I Said So"
  },
  {
    "Name": " Because of Winn-Dixie"
  },
  {
    "Name": " Be Cool"
  },
  {
    "Name": " BFG, The"
  },
  {
    "Name": " Before Night Falls"
  },
  {
    "Name": " Behind the Red Door"
  },
  {
    "Name": " Berget på månens baksida (also known as A Hill on the Dark Side of the Moon)"
  },
  {
    "Name": " Better Luck Tomorrow"
  },
  {
    "Name": " Better Tomorrow II, A"
  },
  {
    "Name": " Better Tomorrow III, A"
  },
  {
    "Name": " Bewitched"
  },
  {
    "Name": " Beyond the Gates"
  },
  {
    "Name": " Big Ass Spider!"
  },
  {
    "Name": " Big Bounce, The"
  },
  {
    "Name": " Big Kahuna, The"
  },
  {
    "Name": " Big Money Hustlas"
  },
  {
    "Name": " Big Shot's Funeral"
  },
  {
    "Name": " Big Time"
  },
  {
    "Name": " Bigger Than Life"
  },
  {
    "Name": " Billy Elliot"
  },
  {
    "Name": " Bingo Long Traveling All-Stars & Motor Kings, The"
  },
  {
    "Name": " Bio-Dome"
  },
  {
    "Name": " Birthday Girl"
  },
  {
    "Name": " Bitch Slap"
  },
  {
    "Name": " Bitter Victory"
  },
  {
    "Name": " Black Cauldron, The"
  },
  {
    "Name": " Black Chicks Talking"
  },
  {
    "Name": " Black Snake Moan"
  },
  {
    "Name": " Black Stallion, The"
  },
  {
    "Name": " Blame It on Rio"
  },
  {
    "Name": " Bless the Child (2000)"
  },
  {
    "Name": " Bless the Child (2003)"
  },
  {
    "Name": " Blind Beast vs. Dwarf"
  },
  {
    "Name": " Blind Side, The"
  },
  {
    "Name": " Blood and Chocolate"
  },
  {
    "Name": " Blood In Blood Out"
  },
  {
    "Name": " Blood of Hussain, The"
  },
  {
    "Name": " BloodRayne"
  },
  {
    "Name": " BloodRayne 2 Deliverence"
  },
  {
    "Name": " Bloodsport"
  },
  {
    "Name": " Blue Car"
  },
  {
    "Name": " Blue Diner, The"
  },
  {
    "Name": " Blue Hill Avenue"
  },
  {
    "Name": " Blue Streak"
  },
  {
    "Name": " Blue Valentine"
  },
  {
    "Name": " Bobby"
  },
  {
    "Name": " Bon Cop, Bad Cop"
  },
  {
    "Name": " Bone Collector, The"
  },
  {
    "Name": " Born to Be Bad (1934)"
  },
  {
    "Name": " Born to Be Bad (1950)"
  },
  {
    "Name": " Bottle Shock"
  },
  {
    "Name": " Bounty Hunter, The (1954)"
  },
  {
    "Name": " Bounty Hunter, The (2010)"
  },
  {
    "Name": " Brain Dead"
  },
  {
    "Name": " Brave Little Toaster, The"
  },
  {
    "Name": " Bread and Milk"
  },
  {
    "Name": " Breakfast of Champions"
  },
  {
    "Name": " Break-Up, The"
  },
  {
    "Name": " Breed, The (2001)"
  },
  {
    "Name": " Breed, The (2006)"
  },
  {
    "Name": " Bride & Prejudice"
  },
  {
    "Name": " Bride of the Wind"
  },
  {
    "Name": " Bridge Too Far, A"
  },
  {
    "Name": " Brief Crossing"
  },
  {
    "Name": " Brigham City"
  },
  {
    "Name": " Bright Young Things"
  },
  {
    "Name": " Bring It On II"
  },
  {
    "Name": " Brink!"
  },
  {
    "Name": " Brokedown Palace"
  },
  {
    "Name": " Bronco Billy"
  },
  {
    "Name": " Bronx Tale, A"
  },
  {
    "Name": " Brother"
  },
  {
    "Name": " Brotherhood of the Wolf"
  },
  {
    "Name": " Brown Sugar"
  },
  {
    "Name": " Brylcreem Boys, The"
  },
  {
    "Name": " Buffalo Soldier"
  },
  {
    "Name": " Bury My Heart at Wounded Knee"
  },
  {
    "Name": " Buying the Cow"
  },
  {
    "Name": " "
  },
  {
    "Name": " Cadillac Records"
  },
  {
    "Name": " Cake Eaters, The"
  },
  {
    "Name": " Camp (1965)"
  },
  {
    "Name": " Camp (2003)"
  },
  {
    "Name": " Candyman"
  },
  {
    "Name": " Cars 3"
  },
  {
    "Name": " Cannibal! The Musical"
  },
  {
    "Name": " Carbon Copy"
  },
  {
    "Name": " Carpool"
  },
  {
    "Name": " Carry On Series, The"
  },
  {
    "Name": " Catch That Kid"
  },
  {
    "Name": " The Castle of Cagliostro"
  },
  {
    "Name": " Cat's Meow, The"
  },
  {
    "Name": " Center Stage"
  },
  {
    "Name": " Chairman of the Board"
  },
  {
    "Name": " Chances Are"
  },
  {
    "Name": " Chandni Bar"
  },
  {
    "Name": " Changeling, The"
  },
  {
    "Name": " Charly"
  },
  {
    "Name": " Chaos"
  },
  {
    "Name": " Cheats"
  },
  {
    "Name": " Chick (1928)"
  },
  {
    "Name": " Chick (1936)"
  },
  {
    "Name": " Chicken Little"
  },
  {
    "Name": " Chisum"
  },
  {
    "Name": " Chopper (film)Chopper"
  },
  {
    "Name": " Christmas Vacation"
  },
  {
    "Name": " City Slickers II"
  },
  {
    "Name": " Cinderella Man"
  },
  {
    "Name": " Clash of the Titans"
  },
  {
    "Name": " Cobra (1925)"
  },
  {
    "Name": " Cobra (1986)"
  },
  {
    "Name": " Cobra (2012)"
  },
  {
    "Name": " Cobra (2014)"
  },
  {
    "Name": " Cobra, The (1967)"
  },
  {
    "Name": " College Road Trip"
  },
  {
    "Name": " Control (1987)"
  },
  {
    "Name": " Control (2004)"
  },
  {
    "Name": " Control (2005)"
  },
  {
    "Name": " Control (2013)"
  },
  {
    "Name": " Conversations with My Gardener"
  },
  {
    "Name": " Confessions of a Teenage Drama Queen"
  },
  {
    "Name": " Confessions of Shopaholic"
  },
  {
    "Name": " Conjuring, The"
  },
  {
    "Name": " Counterfeiters, The"
  },
  {
    "Name": " Courage Under Fire"
  },
  {
    "Name": " Covenant, The"
  },
  {
    "Name": " C.R.A.Z.Y."
  },
  {
    "Name": " Crew, The"
  },
  {
    "Name": " Crocodile Dundee II"
  },
  {
    "Name": " Crow: Salvation, The"
  },
  {
    "Name": " Crow: Wicked Prayer, The"
  },
  {
    "Name": " Cujo"
  },
  {
    "Name": " Cutthroat Island"
  },
  {
    "Name": " Cypher"
  }
]